agent_function_tool-0.1.2.dist-info/licenses/LICENSE
function_tool/__init__.py
function_tool/py.typed
agent_function_tool-0.1.2.dist-info/METADATA
agent_function_tool-0.1.2.dist-info/WHEEL
agent_function_tool-0.1.2.dist-info/top_level.txt
agent_function_tool-0.1.2.dist-info/zip-safe
agent_function_tool-0.1.2.dist-info/RECORD
