Metadata-Version: 2.4
Name: agent_function_tool
Version: 0.1.2
Summary: Universal wrapper for Python functions to be used with LLM function calling
Author-email: Levente Hunyadi <hunyadi@gmail.com>
Maintainer-email: Levente Hunyadi <hunyadi@gmail.com>
License-Expression: MIT
Project-URL: Homepage, https://github.com/hunyadi/function_tool
Project-URL: Source, https://github.com/hunyadi/function_tool
Keywords: ai-agent,large-language-model,function-calling,tool-calling
Classifier: Development Status :: 5 - Production/Stable
Classifier: Intended Audience :: Developers
Classifier: Operating System :: OS Independent
Classifier: Programming Language :: Python :: 3
Classifier: Programming Language :: Python :: 3.10
Classifier: Programming Language :: Python :: 3.11
Classifier: Programming Language :: Python :: 3.12
Classifier: Programming Language :: Python :: 3.13
Classifier: Programming Language :: Python :: 3 :: Only
Classifier: Topic :: Scientific/Engineering :: Artificial Intelligence
Classifier: Topic :: Scientific/Engineering :: Human Machine Interfaces
Classifier: Topic :: Scientific/Engineering :: Interface Engine/Protocol Translator
Classifier: Topic :: File Formats :: JSON :: JSON Schema
Classifier: Topic :: Utilities
Classifier: Typing :: Typed
Requires-Python: >=3.10
License-File: LICENSE
Requires-Dist: pydantic>=2.12
Requires-Dist: typing_extensions>=4.15; python_version < "3.12"
Provides-Extra: dev
Requires-Dist: ruff>=0.14; extra == "dev"
Dynamic: license-file
